{"noiseKey":{"private":{"type":"Buffer","data":"cAtzjR25XPWB1Jpf+xF9mfXQXgSk8QPxTLgQ8kPkHl8="},"public":{"type":"Buffer","data":"OdCyaTVhkzXwRNHxRw9z6TTfw9LRFJ8lt3azucNtgU8="}},"pairingEphemeralKeyPair":{"private":{"type":"Buffer","data":"sE7gQxmJMZULcGC1drlEsoSCwCtoYVSeU5TNycFcelI="},"public":{"type":"Buffer","data":"mvGbwIFR5nelG1JB1vETlc8Jlj6nM/AQuKh7eVeZklY="}},"signedIdentityKey":{"private":{"type":"Buffer","data":"IP7kpHPueLTNrsMOIKOgN2uAA2KdnbZXzgbjr2nCeng="},"public":{"type":"Buffer","data":"J+5npNa7k1p6V1Isqsw0iA1ceUnJ99V7L5I6B/Q5YkA="}},"signedPreKey":{"keyPair":{"private":{"type":"Buffer","data":"oMBR5prZGOtvXtgLuroS6/Xt201TIrh9M5l1qDv0nGk="},"public":{"type":"Buffer","data":"Kqw58XzgO/TRBwGVHYgDplx4kiaJdDwOq+BNgbhAvhU="}},"signature":{"type":"Buffer","data":"sJ3H+ZsugqH9bebxmJDw0stsNeI+SiqqXWcJoBSVkvfTB04rnvjPV3MJ0vZ6SB3SvEqVPWLQHFyFa8S/XWScCA=="},"keyId":1},"registrationId":127,"advSecretKey":"gYVU16DyKFd9jkDEH18b6VmKQYR9ktvCuDD7YDKNDfY=","processedHistoryMessages":[{"key":{"remoteJid":"6737318620@s.whatsapp.net","fromMe":true,"id":"3AED687AA74F3C5E1D53"},"messageTimestamp":1705508178},{"key":{"remoteJid":"6737318620@s.whatsapp.net","fromMe":true,"id":"3A3BF0518EEE2B965F22"},"messageTimestamp":1705508197},{"key":{"remoteJid":"6737318620@s.whatsapp.net","fromMe":true,"id":"3A10A86A8B1BD4832922"},"messageTimestamp":1705508227},{"key":{"remoteJid":"6737318620@s.whatsapp.net","fromMe":true,"id":"3AD2691F6D70DE25ADA3"},"messageTimestamp":1705508263},{"key":{"remoteJid":"6737318620@s.whatsapp.net","fromMe":true,"id":"3A1A9293577336161983"},"messageTimestamp":1705508283}],"nextPreKeyId":31,"firstUnuploadedPreKeyId":31,"accountSyncCounter":1,"accountSettings":{"unarchiveChats":false},"deviceId":"oZUlREOjR7uJZhpTHUGn5Q","phoneId":"51905d76-9519-4e26-8bb9-32a9451bbcbf","identityId":{"type":"Buffer","data":"w53u+58DAifHYNVTtIwMzdKLx5M="},"registered":false,"backupToken":{"type":"Buffer","data":"LkgxRd5EWXdn+2N2+iWf39T3KYs="},"registration":{},"account":{"details":"CLqrnLQIELH6n60GGAIgACgA","accountSignatureKey":"Z3eQdQ07VvnLV0gT5jtxKnz9B8Trz2SKMKwuSAq07SY=","accountSignature":"gIW2/CQPgHs9KTFumkojFYCBH4YwBpZrT4pRaqfo183be33ogPlYdJ6X2iNn9egDvtxZwN3FjJwH5JFRnuGhjA==","deviceSignature":"Y8Gm8LQNUYxCT0jiH/hxdXMcntPvcqpYo1KeGWcueFnybTxsdIGa8yKdf8MRYDlibzsqTZ276W+ukYldczwtBg=="},"me":{"id":"6737318620:32@s.whatsapp.net","name":"nm","jid":"6737318620@s.whatsapp.net"},"signalIdentities":[{"identifier":{"name":"6737318620:32@s.whatsapp.net","deviceId":0},"identifierKey":{"type":"Buffer","data":"BWd3kHUNO1b5y1dIE+Y7cSp8/QfE689kijCsLkgKtO0m"}}],"platform":"iphone","lastAccountSyncTimestamp":1705508149,"myAppStateKeyId":"AAAAALf7"}
